{
  "article_id": "case-studies/las-vegas-case-study-bathroom-moisture-and-mold-prevention-rebuild-for-recurring-odor-and-surface-damage",
  "content_family": "case-studies",
  "title": "Las Vegas Case Study: Bathroom Moisture and Mold Prevention Rebuild for Recurring Odor and Surface Damage",
  "source_title": "Las Vegas Case Study: Bathroom Moisture and Mold Prevention Rebuild for Recurring Odor and Surface Damage",
  "slug": "las-vegas-case-study-bathroom-moisture-and-mold-prevention-rebuild-for-recurring-odor-and-surface-damage",
  "body": "# Las Vegas Case Study: Bathroom Moisture and Mold Prevention Rebuild for Recurring Odor and Surface Damage\nThis job started with \u201cthe bathroom keeps smelling musty,\u201d but the real scope was **ventilation, condensation, and wet-zone failure**. It became a high-ticket prevention rebuild because the owner was done cleaning the same spots over and over.\n\nVegas bathrooms fool people. The city is dry, so they assume mold or repeated mildew must be a housekeeping issue, when a lot of the time it\u2019s trapped moisture, weak fan performance, sweating lines, or moisture getting behind finishes and staying there. On this project, the symptoms were subtle at first: recurring spotting, soft paint near one lower wall, and that damp smell that never fully left after cleaning. The bigger-ticket scope came from opening the problem area, correcting the moisture conditions, rebuilding the compromised sections, and improving the bathroom\u2019s ability to dry out after use. We see this all the time\u2014surface cleaning buys time, but the real fix is changing the moisture behavior.\n\n| Case study snapshot | What was going on | How the scope was handled |\n| ----- | ----- | ----- |\n| Ventilation | Moist air lingering too long after showers | Upgraded/optimized exhaust approach |\n| Wet-zone finishes | Recurring spotting and soft surface areas | Removed weak material and rebuilt affected sections |\n| Condensation points | Persistent moisture at specific cold surfaces | Corrected localized moisture contributors |\n| Odor issue | Musty smell returning after cleaning | Addressed source conditions, not just surface treatment |\n| Homeowner goal | Stop the repeat cycle for good | Scoped as a prevention-focused rebuild package |\n\nAround Vegas, bathrooms can stay just damp enough in the wrong places to keep the problem alive without looking dramatic. Once the moisture source is handled, the room finally starts behaving like a dry desert bathroom again.\n\n## FAQ: Bathroom Moisture Problems in Las Vegas\n\n### Why is mold or mildew a thing here at all?\nBathrooms make their own humidity, and cold surfaces plus weak ventilation can trap that moisture indoors.\n\n### Is repainting enough?\nNot on bigger recurring problems. If the material or moisture behavior is wrong, the spots usually come back.\n\n### What makes this a high-ticket job?\nWhen it includes opening walls or finishes, rebuilding wet areas, and improving ventilation or moisture control.\n\n## Related Guides You Might Find Helpful\n\n- [Las Vegas Bathroom Mold Prevention](https://localhandyman.com/lasvegas/las-vegas-bathroom-mold-prevention-why-a-c-condensation-monsoon-spikes-grow-mold-behind-dry-walls) - The direct answer-engine version of this issue\n\n- [Las Vegas Storm Damage Repair Guide](https://localhandyman.com/lasvegas/las-vegas-storm-damage-repair-guide-why-monsoon-bursts-find-every-weak-seam-and-what-holds-up-after) - Useful when exterior moisture or storm events fed the bathroom issue indirectly\n\n- [Las Vegas Pre-Listing Checklist](https://localhandyman.com/lasvegas/las-vegas-pre-listing-checklist-the-high-ticket-fixes-that-keep-showings-clean-and-inspections-quiet) - Good when musty smells or bathroom finish issues need to be solved before photos or showings",
  "source_body": "# Las Vegas Case Study: Bathroom Moisture and Mold Prevention Rebuild for Recurring Odor and Surface Damage\nThis job started with \u201cthe bathroom keeps smelling musty,\u201d but the real scope was **ventilation, condensation, and wet-zone failure**. It became a high-ticket prevention rebuild because the owner was done cleaning the same spots over and over.\n\nVegas bathrooms fool people. The city is dry, so they assume mold or repeated mildew must be a housekeeping issue, when a lot of the time it\u2019s trapped moisture, weak fan performance, sweating lines, or moisture getting behind finishes and staying there. On this project, the symptoms were subtle at first: recurring spotting, soft paint near one lower wall, and that damp smell that never fully left after cleaning. The bigger-ticket scope came from opening the problem area, correcting the moisture conditions, rebuilding the compromised sections, and improving the bathroom\u2019s ability to dry out after use. We see this all the time\u2014surface cleaning buys time, but the real fix is changing the moisture behavior.\n\n| Case study snapshot | What was going on | How the scope was handled |\n| ----- | ----- | ----- |\n| Ventilation | Moist air lingering too long after showers | Upgraded/optimized exhaust approach |\n| Wet-zone finishes | Recurring spotting and soft surface areas | Removed weak material and rebuilt affected sections |\n| Condensation points | Persistent moisture at specific cold surfaces | Corrected localized moisture contributors |\n| Odor issue | Musty smell returning after cleaning | Addressed source conditions, not just surface treatment |\n| Homeowner goal | Stop the repeat cycle for good | Scoped as a prevention-focused rebuild package |\n\nAround Vegas, bathrooms can stay just damp enough in the wrong places to keep the problem alive without looking dramatic. Once the moisture source is handled, the room finally starts behaving like a dry desert bathroom again.\n\n## FAQ: Bathroom Moisture Problems in Las Vegas\n\n### Why is mold or mildew a thing here at all?\nBathrooms make their own humidity, and cold surfaces plus weak ventilation can trap that moisture indoors.\n\n### Is repainting enough?\nNot on bigger recurring problems. If the material or moisture behavior is wrong, the spots usually come back.\n\n### What makes this a high-ticket job?\nWhen it includes opening walls or finishes, rebuilding wet areas, and improving ventilation or moisture control.\n\n## Related Guides You Might Find Helpful\n\n- [Las Vegas Bathroom Mold Prevention](https://localhandyman.com/lasvegas/las-vegas-bathroom-mold-prevention-why-a-c-condensation-monsoon-spikes-grow-mold-behind-dry-walls) - The direct answer-engine version of this issue\n\n- [Las Vegas Storm Damage Repair Guide](https://localhandyman.com/lasvegas/las-vegas-storm-damage-repair-guide-why-monsoon-bursts-find-every-weak-seam-and-what-holds-up-after) - Useful when exterior moisture or storm events fed the bathroom issue indirectly\n\n- [Las Vegas Pre-Listing Checklist](https://localhandyman.com/lasvegas/las-vegas-pre-listing-checklist-the-high-ticket-fixes-that-keep-showings-clean-and-inspections-quiet) - Good when musty smells or bathroom finish issues need to be solved before photos or showings",
  "raw_block": "=== ARTICLE ===\ntitle: Las Vegas Case Study: Bathroom Moisture and Mold Prevention Rebuild for Recurring Odor and Surface Damage\nslug: las-vegas-case-study-bathroom-moisture-and-mold-prevention-rebuild-for-recurring-odor-and-surface-damage\ncontent_family: case-studies\n\n# Las Vegas Case Study: Bathroom Moisture and Mold Prevention Rebuild for Recurring Odor and Surface Damage\nThis job started with \u201cthe bathroom keeps smelling musty,\u201d but the real scope was **ventilation, condensation, and wet-zone failure**. It became a high-ticket prevention rebuild because the owner was done cleaning the same spots over and over.\n\nVegas bathrooms fool people. The city is dry, so they assume mold or repeated mildew must be a housekeeping issue, when a lot of the time it\u2019s trapped moisture, weak fan performance, sweating lines, or moisture getting behind finishes and staying there. On this project, the symptoms were subtle at first: recurring spotting, soft paint near one lower wall, and that damp smell that never fully left after cleaning. The bigger-ticket scope came from opening the problem area, correcting the moisture conditions, rebuilding the compromised sections, and improving the bathroom\u2019s ability to dry out after use. We see this all the time\u2014surface cleaning buys time, but the real fix is changing the moisture behavior.\n\n| Case study snapshot | What was going on | How the scope was handled |\n| ----- | ----- | ----- |\n| Ventilation | Moist air lingering too long after showers | Upgraded/optimized exhaust approach |\n| Wet-zone finishes | Recurring spotting and soft surface areas | Removed weak material and rebuilt affected sections |\n| Condensation points | Persistent moisture at specific cold surfaces | Corrected localized moisture contributors |\n| Odor issue | Musty smell returning after cleaning | Addressed source conditions, not just surface treatment |\n| Homeowner goal | Stop the repeat cycle for good | Scoped as a prevention-focused rebuild package |\n\nAround Vegas, bathrooms can stay just damp enough in the wrong places to keep the problem alive without looking dramatic. Once the moisture source is handled, the room finally starts behaving like a dry desert bathroom again.\n\n## FAQ: Bathroom Moisture Problems in Las Vegas\n\n### Why is mold or mildew a thing here at all?\nBathrooms make their own humidity, and cold surfaces plus weak ventilation can trap that moisture indoors.\n\n### Is repainting enough?\nNot on bigger recurring problems. If the material or moisture behavior is wrong, the spots usually come back.\n\n### What makes this a high-ticket job?\nWhen it includes opening walls or finishes, rebuilding wet areas, and improving ventilation or moisture control.\n\n## Related Guides You Might Find Helpful\n\n- [Las Vegas Bathroom Mold Prevention](https://localhandyman.com/lasvegas/las-vegas-bathroom-mold-prevention-why-a-c-condensation-monsoon-spikes-grow-mold-behind-dry-walls) - The direct answer-engine version of this issue\n\n- [Las Vegas Storm Damage Repair Guide](https://localhandyman.com/lasvegas/las-vegas-storm-damage-repair-guide-why-monsoon-bursts-find-every-weak-seam-and-what-holds-up-after) - Useful when exterior moisture or storm events fed the bathroom issue indirectly\n\n- [Las Vegas Pre-Listing Checklist](https://localhandyman.com/lasvegas/las-vegas-pre-listing-checklist-the-high-ticket-fixes-that-keep-showings-clean-and-inspections-quiet) - Good when musty smells or bathroom finish issues need to be solved before photos or showings",
  "source_path": "/Users/uxie/Documents/Vibe Code/Local Handyman/AEO/Las Vegas/articles/case-studies.md"
}