{
  "page_type": "general_article",
  "faq_present": false,
  "table_present": true,
  "topic": "Lone Mountain Handyman: High-Ticket Repair Packages for Long Exterior Runs, Gates, and Finish Work That Shows",
  "excerpt": "What we see up there is different from a tighter in-town tract: longer side yards, bigger perimeter runs, driveway gates that get fussy, and interior finish issues that stand out because the homes often have cleaner sightlines and stronger natural light. Underneath, the valley\u2019s native soils are shallow, well-drained alluvial soils with carbonates/caliche, so small movement can still show up as sticking doors, recurring drywall cracks, and fence drift even when nothing looks dramatic. Then Vegas weather does the rest\u2014extreme heat, strong sun, wind, and monsoon-season storm bursts stress caulk lines, hardware, coatings, and drainage details all at once. In Lone Mountain, the durable fix is usually a high-ticket bundled scope: tune the openings, stabilize the wall finish, reset the exterior hardware, and correct the water path so the same symptom doesn\u2019t come right back after the next hot spell.",
  "faq_pairs": [],
  "markdown_tables": [
    "| High-ticket Lone Mountain package | What it usually includes | Representative total |\n| ----- | ----- | ----- |\n| Whole-house punch-list reset | doors, hardware, wall repair, trim, caulk, second-pass details | $2,500\u2013$7,500 |\n| Exterior perimeter package | gate tuning, fence corrections, latch geometry, hardware reset | $2,000\u2013$8,500 |\n| Multi-room wall and ceiling finish scope | recurring cracks, wide floats, texture blending, clean finish prep | $2,000\u2013$8,000 |\n| Trim and seal rebuild package | sun-baked trim repairs, resealing, fascia/soffit touchpoints | $2,500\u2013$9,500 |\n| Water-control and storm-prep bundle | discharge fixes, splash-back corrections, exterior reseals | $2,000\u2013$8,500 |\n| Pre-listing \u201cshow-ready\u201d project | high-visibility fixes inside and out, plus final punch pass | $3,500\u2013$12,000 |"
  ]
}