{
  "page_type": "faq_page",
  "primary_topic": "Bathroom Condensation in Las Vegas",
  "about": [
    "bathroom repair",
    "Las Vegas repair",
    "technical repair guidance"
  ],
  "mentions": [
    "Las Vegas",
    "Nevada",
    "Las Vegas repair",
    "technical repair guidance"
  ],
  "answer_summary": "This is one of the easiest issues to misread. People assume a desert bathroom should dry instantly, so if it smells musty they think it is just cleaning or caulk. But bathrooms create their own humidity",
  "speakable_summary": "This is one of the easiest issues to misread. People assume a desert bathroom should dry instantly, so if it smells musty they think it is just cleaning or caulk",
  "questions_answered": [
    "Why does this happen in Las Vegas at all?",
    "Is this just a cleaning problem?",
    "What makes it a high-ticket job?"
  ],
  "service_area": [
    "Summerlin North",
    "Summerlin South",
    "Summerlin West",
    "Queensridge",
    "Centennial Hills",
    "Lone Mountain",
    "Angel Park",
    "Desert Shores",
    "Rancho",
    "Downtown Las Vegas"
  ],
  "article_section_labels": [
    "Frequently Asked Questions",
    "Related Guides You Might Find Helpful",
    "Cost and Scope Table"
  ]
}