[
  {
    "@context": "https://schema.org",
    "@type": "BlogPosting",
    "headline": "Centennial Hills Handyman: High-Ticket Repair Packages for Bigger Homes, Exterior Wear, and Whole-House Punch Lists",
    "description": "Centennial Hills is positioned as a spacious, family-friendly northwest Las Vegas community with newer housing and room to spread out",
    "abstract": "Centennial Hills is positioned as a spacious, family-friendly northwest Las Vegas community with newer housing and room to spread out, and that changes the repair pattern a bit. Instead of one tiny isolated problem",
    "image": [
      "https://assets.cdn.filesafe.space/ZsBUSW0nlx5d5Mjpk3ph/media/e3d95de1-5dcd-4b65-9ab0-d6a39473eb66.jpg",
      "https://assets.cdn.filesafe.space/ZsBUSW0nlx5d5Mjpk3ph/media/47b8b904-4eb2-45e4-8923-14076f8e2670.jpg"
    ],
    "mainEntityOfPage": "https://localhandyman.com/lasvegas/centennial-hills-handyman-high-ticket-repair-packages-for-bigger-homes-exterior-wear-and-whole-house-punch-lists",
    "datePublished": "2026-03-03",
    "articleSection": [
      "Related Guides You Might Find Helpful",
      "Cost and Scope Table"
    ],
    "about": [
      {
        "@type": "Thing",
        "name": "handyman services"
      },
      {
        "@type": "Thing",
        "name": "service area repairs"
      }
    ],
    "mentions": [
      {
        "@type": "Thing",
        "name": "Las Vegas"
      },
      {
        "@type": "Thing",
        "name": "Nevada"
      },
      {
        "@type": "Thing",
        "name": "service area repairs"
      }
    ],
    "author": {
      "@type": "Organization",
      "name": "Local Handyman Las Vegas"
    },
    "publisher": {
      "@type": "Organization",
      "name": "Local Handyman Las Vegas",
      "logo": {
        "@type": "ImageObject",
        "url": "https://images.leadconnectorhq.com/image/f_webp/q_80/r_1200/u_https://assets.cdn.filesafe.space/ZsBUSW0nlx5d5Mjpk3ph/media/675af3438d3fea52d8157c18.png"
      }
    }
  },
  {
    "@context": "https://schema.org",
    "@type": "LocalBusiness",
    "name": "Local Handyman Las Vegas",
    "url": "https://localhandyman.com/lasvegas",
    "telephone": "(702) 766-7228",
    "address": {
      "@type": "PostalAddress",
      "streetAddress": "732 South 6th Street 4523",
      "addressLocality": "Las Vegas",
      "addressRegion": "Nevada",
      "postalCode": "89101",
      "addressCountry": "USA"
    },
    "areaServed": [
      "Summerlin North",
      "Summerlin South",
      "Summerlin West",
      "Queensridge",
      "Centennial Hills",
      "Lone Mountain",
      "Angel Park",
      "Desert Shores",
      "Rancho",
      "Downtown Las Vegas"
    ],
    "image": "https://images.leadconnectorhq.com/image/f_webp/q_80/r_1200/u_https://assets.cdn.filesafe.space/ZsBUSW0nlx5d5Mjpk3ph/media/675af3438d3fea52d8157c18.png"
  }
]